{
  "entrypoints": [
    "main"
  ],
  "origins": {
    "165": [
      3624,
      7928,
      8731,
      9311,
      165
    ],
    "504": [
      697,
      2334,
      3624,
      504
    ],
    "697": [
      504,
      2334,
      3624,
      4070,
      7367,
      8021,
      697
    ],
    "859": [
      4377,
      9169,
      859
    ],
    "878": [
      878
    ],
    "1031": [
      1031
    ],
    "1679": [
      3624,
      8731,
      1679
    ],
    "2038": [
      2038
    ],
    "2130": [
      2130
    ],
    "2334": [
      504,
      697,
      3624,
      4070,
      8021,
      2334
    ],
    "2588": [
      2588
    ],
    "2850": [
      2850
    ],
    "3042": [
      3042
    ],
    "3201": [
      3201
    ],
    "3624": [
      165,
      504,
      697,
      1679,
      2334,
      4070,
      5447,
      5518,
      7367,
      7598,
      7999,
      8021,
      8731,
      8811,
      9311,
      3624
    ],
    "4070": [
      697,
      2334,
      3624,
      8021,
      4070
    ],
    "4293": [
      8021,
      4293
    ],
    "4377": [
      859,
      4377
    ],
    "4736": [
      4736
    ],
    "5187": [
      5187
    ],
    "5359": [
      5359
    ],
    "5378": [
      5378
    ],
    "5447": [
      3624,
      8731,
      5447
    ],
    "5518": [
      3624,
      8731,
      5518
    ],
    "5895": [
      5895
    ],
    "5944": [
      5944
    ],
    "5982": [
      5982
    ],
    "6235": [
      6235
    ],
    "6427": [
      6427
    ],
    "6500": [
      6500
    ],
    "6550": [
      6550
    ],
    "7333": [
      7333
    ],
    "7367": [
      697,
      3624,
      7367
    ],
    "7598": [
      3624,
      8731,
      7598
    ],
    "7928": [
      165,
      7928
    ],
    "7999": [
      3624,
      8731,
      7999
    ],
    "8021": [
      697,
      2334,
      3624,
      4070,
      4293,
      8021
    ],
    "8335": [
      8335
    ],
    "8644": [
      8644
    ],
    "8659": [
      8659
    ],
    "8731": [
      165,
      1679,
      3624,
      5447,
      5518,
      7598,
      7999,
      8811,
      9311,
      8731
    ],
    "8811": [
      3624,
      8731,
      8811
    ],
    "8894": [
      8894
    ],
    "9169": [
      859,
      9169
    ],
    "9311": [
      165,
      3624,
      8731,
      9311
    ],
    "17896441": [
      1869,
      8401
    ],
    "29828528": [
      9257
    ],
    "85423447": [
      1402
    ],
    "main": [
      1869,
      5354,
      8792
    ],
    "runtime~main": [
      1869,
      8792,
      5354
    ],
    "0058b4c6": [
      849
    ],
    "01284f3d": [
      9323
    ],
    "1df93b7f": [
      4583
    ],
    "20321f00": [
      6783
    ],
    "25d55464": [
      3664
    ],
    "2f82f38d": [
      3104
    ],
    "3dcd629a": [
      3601
    ],
    "4a606758": [
      8870
    ],
    "4e036b1b": [
      8732
    ],
    "52c6a66b": [
      7336
    ],
    "54793c33": [
      8316
    ],
    "5877ecc2": [
      2629
    ],
    "5e95c892": [
      9647
    ],
    "608d6ba6": [
      7424
    ],
    "6641e852": [
      376
    ],
    "6dd807a0": [
      5001
    ],
    "7003cede": [
      8400
    ],
    "746b030a": [
      3912
    ],
    "7e3d3696": [
      2744
    ],
    "8283fd28": [
      5718
    ],
    "a7456010": [
      1235
    ],
    "a7722a3a": [
      9451
    ],
    "a7bd4aaa": [
      7098
    ],
    "a94703ab": [
      1869,
      9048
    ],
    "aba21aa0": [
      5742
    ],
    "abe1e3e5": [
      90
    ],
    "b01e02b7": [
      4704
    ],
    "b13708f1": [
      4697
    ],
    "bb544952": [
      9552
    ],
    "bce7536b": [
      4954
    ],
    "c87e06fc": [
      6721
    ],
    "c8bd9b9f": [
      304
    ],
    "cb31427e": [
      5242
    ],
    "cc404703": [
      5981
    ],
    "cd3ef3a4": [
      3840
    ],
    "d2fafd79": [
      9628
    ],
    "ddafc43e": [
      4659
    ],
    "ed830afd": [
      184
    ],
    "f5d53ad7": [
      2918
    ],
    "f652cf6a": [
      1662
    ],
    "fa8fa488": [
      2829
    ],
    "fe1ef7c1": [
      6387
    ],
    "styles": [
      5354,
      8401,
      8792,
      9048,
      1869
    ]
  },
  "assets": {
    "90": {
      "js": [
        {
          "file": "assets/js/abe1e3e5.a85ca2cd.js",
          "hash": "0cbce672b1ed3683",
          "publicPath": "/assets/js/abe1e3e5.a85ca2cd.js"
        }
      ]
    },
    "165": {
      "js": [
        {
          "file": "assets/js/165.9f1ef0ea.js",
          "hash": "7ee412a7f5250506",
          "publicPath": "/assets/js/165.9f1ef0ea.js"
        }
      ]
    },
    "184": {
      "js": [
        {
          "file": "assets/js/ed830afd.7c29856a.js",
          "hash": "834bda9115a95ab2",
          "publicPath": "/assets/js/ed830afd.7c29856a.js"
        }
      ]
    },
    "304": {
      "js": [
        {
          "file": "assets/js/c8bd9b9f.3378182f.js",
          "hash": "42b8314734c45b23",
          "publicPath": "/assets/js/c8bd9b9f.3378182f.js"
        }
      ]
    },
    "376": {
      "js": [
        {
          "file": "assets/js/6641e852.7a7fffe2.js",
          "hash": "777019619e971218",
          "publicPath": "/assets/js/6641e852.7a7fffe2.js"
        }
      ]
    },
    "504": {
      "js": [
        {
          "file": "assets/js/504.8ab79c74.js",
          "hash": "85413979d9fbc10d",
          "publicPath": "/assets/js/504.8ab79c74.js"
        }
      ]
    },
    "697": {
      "js": [
        {
          "file": "assets/js/697.fe64af96.js",
          "hash": "09aa4264120c0e5e",
          "publicPath": "/assets/js/697.fe64af96.js"
        }
      ]
    },
    "849": {
      "js": [
        {
          "file": "assets/js/0058b4c6.deddbcbf.js",
          "hash": "c3634d42443d140e",
          "publicPath": "/assets/js/0058b4c6.deddbcbf.js"
        }
      ]
    },
    "859": {
      "js": [
        {
          "file": "assets/js/859.a7015824.js",
          "hash": "10bf5daf2dc79d67",
          "publicPath": "/assets/js/859.a7015824.js"
        }
      ]
    },
    "878": {
      "js": [
        {
          "file": "assets/js/878.4bf50ca4.js",
          "hash": "bf84d58f142314bb",
          "publicPath": "/assets/js/878.4bf50ca4.js"
        }
      ]
    },
    "1031": {
      "js": [
        {
          "file": "assets/js/1031.9bae6193.js",
          "hash": "508a742d1c1d8241",
          "publicPath": "/assets/js/1031.9bae6193.js"
        }
      ]
    },
    "1235": {
      "js": [
        {
          "file": "assets/js/a7456010.04f37ec4.js",
          "hash": "ba3f76e040ce75d0",
          "publicPath": "/assets/js/a7456010.04f37ec4.js"
        }
      ]
    },
    "1402": {
      "js": [
        {
          "file": "assets/js/85423447.9d93f51a.js",
          "hash": "c240f513a39a0f16",
          "publicPath": "/assets/js/85423447.9d93f51a.js"
        }
      ]
    },
    "1662": {
      "js": [
        {
          "file": "assets/js/f652cf6a.2c82a4de.js",
          "hash": "e7a725d3e95cb234",
          "publicPath": "/assets/js/f652cf6a.2c82a4de.js"
        }
      ]
    },
    "1679": {
      "js": [
        {
          "file": "assets/js/1679.22c9ebce.js",
          "hash": "72158b07852c75ae",
          "publicPath": "/assets/js/1679.22c9ebce.js"
        }
      ]
    },
    "1869": {
      "css": [
        {
          "file": "assets/css/styles.5d82ab93.css",
          "hash": "3fd85cb8a2215b74",
          "publicPath": "/assets/css/styles.5d82ab93.css"
        }
      ]
    },
    "2038": {
      "js": [
        {
          "file": "assets/js/2038.f4846ccc.js",
          "hash": "30e2eaea078ca813",
          "publicPath": "/assets/js/2038.f4846ccc.js"
        }
      ]
    },
    "2130": {
      "js": [
        {
          "file": "assets/js/2130.396f486f.js",
          "hash": "01f436ac434fb0c8",
          "publicPath": "/assets/js/2130.396f486f.js"
        }
      ]
    },
    "2334": {
      "js": [
        {
          "file": "assets/js/2334.802ecf4c.js",
          "hash": "b62d740fe19016fc",
          "publicPath": "/assets/js/2334.802ecf4c.js"
        }
      ]
    },
    "2588": {
      "js": [
        {
          "file": "assets/js/2588.02707b4a.js",
          "hash": "2f93aa20a6c0f47b",
          "publicPath": "/assets/js/2588.02707b4a.js"
        }
      ]
    },
    "2629": {
      "js": [
        {
          "file": "assets/js/5877ecc2.0410c2f7.js",
          "hash": "782d854bfbc25641",
          "publicPath": "/assets/js/5877ecc2.0410c2f7.js"
        }
      ]
    },
    "2744": {
      "js": [
        {
          "file": "assets/js/7e3d3696.0aa5f9b3.js",
          "hash": "91fbe85f52583d42",
          "publicPath": "/assets/js/7e3d3696.0aa5f9b3.js"
        }
      ]
    },
    "2829": {
      "js": [
        {
          "file": "assets/js/fa8fa488.511b85e7.js",
          "hash": "de36cc02e2ac8c5e",
          "publicPath": "/assets/js/fa8fa488.511b85e7.js"
        }
      ]
    },
    "2850": {
      "js": [
        {
          "file": "assets/js/2850.b6edee7a.js",
          "hash": "194f863d28d72af5",
          "publicPath": "/assets/js/2850.b6edee7a.js"
        }
      ]
    },
    "2918": {
      "js": [
        {
          "file": "assets/js/f5d53ad7.d34575f2.js",
          "hash": "edc6f663d463741a",
          "publicPath": "/assets/js/f5d53ad7.d34575f2.js"
        }
      ]
    },
    "3042": {
      "js": [
        {
          "file": "assets/js/3042.acfed876.js",
          "hash": "3bd8a8bada3220e1",
          "publicPath": "/assets/js/3042.acfed876.js"
        }
      ]
    },
    "3104": {
      "js": [
        {
          "file": "assets/js/2f82f38d.b42b3fea.js",
          "hash": "875a997775f3312b",
          "publicPath": "/assets/js/2f82f38d.b42b3fea.js"
        }
      ]
    },
    "3201": {
      "js": [
        {
          "file": "assets/js/3201.d39d579b.js",
          "hash": "e2679cf1e7fb8923",
          "publicPath": "/assets/js/3201.d39d579b.js"
        }
      ]
    },
    "3601": {
      "js": [
        {
          "file": "assets/js/3dcd629a.7ac17d04.js",
          "hash": "b7dca86d839a9dcb",
          "publicPath": "/assets/js/3dcd629a.7ac17d04.js"
        }
      ]
    },
    "3624": {
      "js": [
        {
          "file": "assets/js/3624.d7a54e34.js",
          "hash": "8eed5486d795e466",
          "publicPath": "/assets/js/3624.d7a54e34.js"
        }
      ]
    },
    "3664": {
      "js": [
        {
          "file": "assets/js/25d55464.e0aade24.js",
          "hash": "ae8e0c921d65892f",
          "publicPath": "/assets/js/25d55464.e0aade24.js"
        }
      ]
    },
    "3840": {
      "js": [
        {
          "file": "assets/js/cd3ef3a4.66a5aa34.js",
          "hash": "8178dded8a0f3fcd",
          "publicPath": "/assets/js/cd3ef3a4.66a5aa34.js"
        }
      ]
    },
    "3912": {
      "js": [
        {
          "file": "assets/js/746b030a.d068f73e.js",
          "hash": "81ca5195e0aac912",
          "publicPath": "/assets/js/746b030a.d068f73e.js"
        }
      ]
    },
    "4070": {
      "js": [
        {
          "file": "assets/js/4070.d2a28542.js",
          "hash": "cee29fa6c622298a",
          "publicPath": "/assets/js/4070.d2a28542.js"
        }
      ]
    },
    "4293": {
      "js": [
        {
          "file": "assets/js/4293.a5f29744.js",
          "hash": "e42a12b5e11f466b",
          "publicPath": "/assets/js/4293.a5f29744.js"
        }
      ]
    },
    "4377": {
      "js": [
        {
          "file": "assets/js/4377.767d2bf9.js",
          "hash": "f2454eed866538d5",
          "publicPath": "/assets/js/4377.767d2bf9.js"
        }
      ]
    },
    "4583": {
      "js": [
        {
          "file": "assets/js/1df93b7f.a56c1d16.js",
          "hash": "0167b91eefe24e45",
          "publicPath": "/assets/js/1df93b7f.a56c1d16.js"
        }
      ]
    },
    "4659": {
      "js": [
        {
          "file": "assets/js/ddafc43e.3e477939.js",
          "hash": "532d2dc62b273f83",
          "publicPath": "/assets/js/ddafc43e.3e477939.js"
        }
      ]
    },
    "4697": {
      "js": [
        {
          "file": "assets/js/b13708f1.5278ff50.js",
          "hash": "b63b3dfb58336a5a",
          "publicPath": "/assets/js/b13708f1.5278ff50.js"
        }
      ]
    },
    "4704": {
      "js": [
        {
          "file": "assets/js/b01e02b7.3d4dd279.js",
          "hash": "6a48385dc04a8a47",
          "publicPath": "/assets/js/b01e02b7.3d4dd279.js"
        }
      ]
    },
    "4736": {
      "js": [
        {
          "file": "assets/js/4736.898eed0d.js",
          "hash": "e748beeac0d77d3c",
          "publicPath": "/assets/js/4736.898eed0d.js"
        }
      ]
    },
    "4954": {
      "js": [
        {
          "file": "assets/js/bce7536b.7df064bd.js",
          "hash": "f8afea109312b38c",
          "publicPath": "/assets/js/bce7536b.7df064bd.js"
        }
      ]
    },
    "5001": {
      "js": [
        {
          "file": "assets/js/6dd807a0.6d868fa0.js",
          "hash": "908a0a3b0eefbacd",
          "publicPath": "/assets/js/6dd807a0.6d868fa0.js"
        }
      ]
    },
    "5187": {
      "js": [
        {
          "file": "assets/js/5187.348c154f.js",
          "hash": "0d27356a1a3fe054",
          "publicPath": "/assets/js/5187.348c154f.js"
        }
      ]
    },
    "5242": {
      "js": [
        {
          "file": "assets/js/cb31427e.f3820498.js",
          "hash": "67c310f5585d3125",
          "publicPath": "/assets/js/cb31427e.f3820498.js"
        }
      ]
    },
    "5354": {
      "js": [
        {
          "file": "assets/js/runtime~main.f0541da8.js",
          "hash": "b9f4a4e6bb5d9107",
          "publicPath": "/assets/js/runtime~main.f0541da8.js"
        }
      ]
    },
    "5359": {
      "js": [
        {
          "file": "assets/js/5359.a4f4258d.js",
          "hash": "567f0e9ff702948d",
          "publicPath": "/assets/js/5359.a4f4258d.js"
        }
      ]
    },
    "5378": {
      "js": [
        {
          "file": "assets/js/5378.17044952.js",
          "hash": "6567d575dd33ddad",
          "publicPath": "/assets/js/5378.17044952.js"
        }
      ]
    },
    "5447": {
      "js": [
        {
          "file": "assets/js/5447.7e4a61ed.js",
          "hash": "a9a1ca614ea10c13",
          "publicPath": "/assets/js/5447.7e4a61ed.js"
        }
      ]
    },
    "5518": {
      "js": [
        {
          "file": "assets/js/5518.c22fbdea.js",
          "hash": "55a4e6ebdc0fc573",
          "publicPath": "/assets/js/5518.c22fbdea.js"
        }
      ]
    },
    "5718": {
      "js": [
        {
          "file": "assets/js/8283fd28.2fd7c279.js",
          "hash": "605ff0abac6b9146",
          "publicPath": "/assets/js/8283fd28.2fd7c279.js"
        }
      ]
    },
    "5742": {
      "js": [
        {
          "file": "assets/js/aba21aa0.0d4a0e23.js",
          "hash": "2163078805a14aad",
          "publicPath": "/assets/js/aba21aa0.0d4a0e23.js"
        }
      ]
    },
    "5895": {
      "js": [
        {
          "file": "assets/js/5895.353d406c.js",
          "hash": "fdd6fab0776dcc13",
          "publicPath": "/assets/js/5895.353d406c.js"
        }
      ]
    },
    "5944": {
      "js": [
        {
          "file": "assets/js/5944.34eea5e6.js",
          "hash": "99a06b079dac81b1",
          "publicPath": "/assets/js/5944.34eea5e6.js"
        }
      ]
    },
    "5981": {
      "js": [
        {
          "file": "assets/js/cc404703.6920da6a.js",
          "hash": "47d1d22163e6c0b0",
          "publicPath": "/assets/js/cc404703.6920da6a.js"
        }
      ]
    },
    "5982": {
      "js": [
        {
          "file": "assets/js/5982.45a34a53.js",
          "hash": "a49f470d03d076d3",
          "publicPath": "/assets/js/5982.45a34a53.js"
        }
      ]
    },
    "6235": {
      "js": [
        {
          "file": "assets/js/6235.c36a341e.js",
          "hash": "28f5420ef504c842",
          "publicPath": "/assets/js/6235.c36a341e.js"
        }
      ]
    },
    "6387": {
      "js": [
        {
          "file": "assets/js/fe1ef7c1.c5c9888b.js",
          "hash": "30691ee83cb7e5d9",
          "publicPath": "/assets/js/fe1ef7c1.c5c9888b.js"
        }
      ]
    },
    "6427": {
      "js": [
        {
          "file": "assets/js/6427.2a907ede.js",
          "hash": "ab4b245158bf0197",
          "publicPath": "/assets/js/6427.2a907ede.js"
        }
      ]
    },
    "6500": {
      "js": [
        {
          "file": "assets/js/6500.f1d306cb.js",
          "hash": "767f35a46ca16956",
          "publicPath": "/assets/js/6500.f1d306cb.js"
        }
      ]
    },
    "6550": {
      "js": [
        {
          "file": "assets/js/6550.984bb9bf.js",
          "hash": "2b5ab8f22aa17c95",
          "publicPath": "/assets/js/6550.984bb9bf.js"
        }
      ]
    },
    "6721": {
      "js": [
        {
          "file": "assets/js/c87e06fc.f3a0aede.js",
          "hash": "8d6e085a04f74ecf",
          "publicPath": "/assets/js/c87e06fc.f3a0aede.js"
        }
      ]
    },
    "6783": {
      "js": [
        {
          "file": "assets/js/20321f00.cc46e1dd.js",
          "hash": "c70ec6ac7482a7d9",
          "publicPath": "/assets/js/20321f00.cc46e1dd.js"
        }
      ]
    },
    "7098": {
      "js": [
        {
          "file": "assets/js/a7bd4aaa.10d7b6ea.js",
          "hash": "ecd1f93f9c8d25c0",
          "publicPath": "/assets/js/a7bd4aaa.10d7b6ea.js"
        }
      ]
    },
    "7333": {
      "js": [
        {
          "file": "assets/js/7333.22a8641a.js",
          "hash": "0e336e7e11e89264",
          "publicPath": "/assets/js/7333.22a8641a.js"
        }
      ]
    },
    "7336": {
      "js": [
        {
          "file": "assets/js/52c6a66b.1f40b28f.js",
          "hash": "3431ee06d1cfb0ea",
          "publicPath": "/assets/js/52c6a66b.1f40b28f.js"
        }
      ]
    },
    "7367": {
      "js": [
        {
          "file": "assets/js/7367.3dae7516.js",
          "hash": "ef8434e246a9b9fb",
          "publicPath": "/assets/js/7367.3dae7516.js"
        }
      ]
    },
    "7424": {
      "js": [
        {
          "file": "assets/js/608d6ba6.e34d4ffc.js",
          "hash": "0e635424f2a0441a",
          "publicPath": "/assets/js/608d6ba6.e34d4ffc.js"
        }
      ]
    },
    "7598": {
      "js": [
        {
          "file": "assets/js/7598.c414a9be.js",
          "hash": "1ff6d91f0957170e",
          "publicPath": "/assets/js/7598.c414a9be.js"
        }
      ]
    },
    "7928": {
      "js": [
        {
          "file": "assets/js/7928.85f0a632.js",
          "hash": "2b58398ecff8ad7e",
          "publicPath": "/assets/js/7928.85f0a632.js"
        }
      ]
    },
    "7999": {
      "js": [
        {
          "file": "assets/js/7999.b0e0915c.js",
          "hash": "012e4f672c09a472",
          "publicPath": "/assets/js/7999.b0e0915c.js"
        }
      ]
    },
    "8021": {
      "js": [
        {
          "file": "assets/js/8021.23f86f8c.js",
          "hash": "0c67fe25707fd290",
          "publicPath": "/assets/js/8021.23f86f8c.js"
        }
      ]
    },
    "8316": {
      "js": [
        {
          "file": "assets/js/54793c33.d86e59ba.js",
          "hash": "b5ec5637f7ebb693",
          "publicPath": "/assets/js/54793c33.d86e59ba.js"
        }
      ]
    },
    "8335": {
      "js": [
        {
          "file": "assets/js/8335.c0fe9319.js",
          "hash": "5c6155cd798fe249",
          "publicPath": "/assets/js/8335.c0fe9319.js"
        }
      ]
    },
    "8400": {
      "js": [
        {
          "file": "assets/js/7003cede.05babbbe.js",
          "hash": "74d2c9079cf9f035",
          "publicPath": "/assets/js/7003cede.05babbbe.js"
        }
      ]
    },
    "8401": {
      "js": [
        {
          "file": "assets/js/17896441.7e0b3260.js",
          "hash": "383064178a0bc47c",
          "publicPath": "/assets/js/17896441.7e0b3260.js"
        }
      ]
    },
    "8644": {
      "js": [
        {
          "file": "assets/js/8644.464508e8.js",
          "hash": "ac6d23e141435fb7",
          "publicPath": "/assets/js/8644.464508e8.js"
        }
      ]
    },
    "8659": {
      "js": [
        {
          "file": "assets/js/8659.71cee7b5.js",
          "hash": "5e23afcd593711ff",
          "publicPath": "/assets/js/8659.71cee7b5.js"
        }
      ]
    },
    "8731": {
      "js": [
        {
          "file": "assets/js/8731.ead4d850.js",
          "hash": "63873e65f3199478",
          "publicPath": "/assets/js/8731.ead4d850.js"
        }
      ]
    },
    "8732": {
      "js": [
        {
          "file": "assets/js/4e036b1b.aaf80a9b.js",
          "hash": "e14a01d0a4e2b48b",
          "publicPath": "/assets/js/4e036b1b.aaf80a9b.js"
        }
      ]
    },
    "8792": {
      "js": [
        {
          "file": "assets/js/main.303139c1.js",
          "hash": "1d7ee6bf3aaa303c",
          "publicPath": "/assets/js/main.303139c1.js"
        }
      ]
    },
    "8811": {
      "js": [
        {
          "file": "assets/js/8811.df7031d8.js",
          "hash": "ffd1e567323790b2",
          "publicPath": "/assets/js/8811.df7031d8.js"
        }
      ]
    },
    "8870": {
      "js": [
        {
          "file": "assets/js/4a606758.a949684e.js",
          "hash": "eb619b58d21114f7",
          "publicPath": "/assets/js/4a606758.a949684e.js"
        }
      ]
    },
    "8894": {
      "js": [
        {
          "file": "assets/js/8894.84fe338b.js",
          "hash": "cda395913a650b59",
          "publicPath": "/assets/js/8894.84fe338b.js"
        }
      ]
    },
    "9048": {
      "js": [
        {
          "file": "assets/js/a94703ab.d7d13d32.js",
          "hash": "7fa106dd1fb4d68b",
          "publicPath": "/assets/js/a94703ab.d7d13d32.js"
        }
      ]
    },
    "9169": {
      "js": [
        {
          "file": "assets/js/9169.022fc660.js",
          "hash": "c90186e3b7d39def",
          "publicPath": "/assets/js/9169.022fc660.js"
        }
      ]
    },
    "9257": {
      "js": [
        {
          "file": "assets/js/29828528.17bbfc2c.js",
          "hash": "6d33a1506b7d5f44",
          "publicPath": "/assets/js/29828528.17bbfc2c.js"
        }
      ]
    },
    "9311": {
      "js": [
        {
          "file": "assets/js/9311.80c29ae7.js",
          "hash": "c6e5abbe5d8cfd9d",
          "publicPath": "/assets/js/9311.80c29ae7.js"
        }
      ]
    },
    "9323": {
      "js": [
        {
          "file": "assets/js/01284f3d.8a1b89d2.js",
          "hash": "a5dd53b46a962d53",
          "publicPath": "/assets/js/01284f3d.8a1b89d2.js"
        }
      ]
    },
    "9451": {
      "js": [
        {
          "file": "assets/js/a7722a3a.3bd15d4c.js",
          "hash": "db68633db2b5da71",
          "publicPath": "/assets/js/a7722a3a.3bd15d4c.js"
        }
      ]
    },
    "9552": {
      "js": [
        {
          "file": "assets/js/bb544952.309c4f67.js",
          "hash": "32b22c1f9440d5d8",
          "publicPath": "/assets/js/bb544952.309c4f67.js"
        }
      ]
    },
    "9628": {
      "js": [
        {
          "file": "assets/js/d2fafd79.f8480458.js",
          "hash": "14fd202a196ac540",
          "publicPath": "/assets/js/d2fafd79.f8480458.js"
        }
      ]
    },
    "9647": {
      "js": [
        {
          "file": "assets/js/5e95c892.37aca965.js",
          "hash": "cf29e4099fd4ded4",
          "publicPath": "/assets/js/5e95c892.37aca965.js"
        }
      ]
    }
  }
}